hermes_client/__init__.py
hermes_client/base.py
hermes_client/forecast.py
hermes_client/forecastseries.py
hermes_client/hermes.py
hermes_client/modelrun.py
hermes_client/schemas.py
hermes_client/utils.py
hermes_client/tests/conftest.py
hermes_client/tests/test_forecastseries.py
hermes_client/tests/test_hermes.py
hermes_client/tests/data/forecasts.json
hermes_client/tests/data/forecastseries.json
hermes_client/tests/data/injectiontemplates.json
hermes_client/tests/data/modelconfigs.json
hermes_client/tests/data/project.json
hermes_client-1.0.1.dist-info/licenses/LICENSE
hermes_client-1.0.1.dist-info/METADATA
hermes_client-1.0.1.dist-info/WHEEL
hermes_client-1.0.1.dist-info/top_level.txt
hermes_client-1.0.1.dist-info/RECORD
