Metadata-Version: 2.4
Name: hermes-client
Version: 1.0.1
Summary: Python client library for the HERMES web service
Author-email: Nicolas Schmid <nicolas.schmid@sed.ethz.ch>
License:                     GNU AFFERO GENERAL PUBLIC LICENSE
Project-URL: Documentation, https://hermes-client.readthedocs.io/
Project-URL: Repository, https://github.com/swiss-seismological-service/hermes-client
Project-URL: Issues, https://github.com/swiss-seismological-service/hermes-client/issues
Classifier: Environment :: Console
Classifier: Intended Audience :: Science/Research
Classifier: Intended Audience :: Education
Classifier: Operating System :: OS Independent
Classifier: License :: OSI Approved :: GNU Affero General Public License v3
Classifier: Programming Language :: Python :: 3
Classifier: Programming Language :: Python :: 3.12
Classifier: Programming Language :: Python :: 3.13
Classifier: Topic :: Scientific/Engineering
Classifier: Topic :: Scientific/Engineering :: Physics
Requires-Python: >=3.12
License-File: LICENSE
Requires-Dist: pandas
Requires-Dist: pydantic
Requires-Dist: requests
Requires-Dist: rich
Requires-Dist: seismostats>=1.0.1
Requires-Dist: shapely
Requires-Dist: hydws-client
Provides-Extra: dev
Requires-Dist: build; extra == "dev"
Requires-Dist: docutils==0.19; extra == "dev"
Requires-Dist: flake8; extra == "dev"
Requires-Dist: isort; extra == "dev"
Requires-Dist: myst-parser; extra == "dev"
Requires-Dist: pandoc; extra == "dev"
Requires-Dist: pydata-sphinx-theme; extra == "dev"
Requires-Dist: pytest-cov; extra == "dev"
Requires-Dist: pytest; extra == "dev"
Requires-Dist: responses; extra == "dev"
Requires-Dist: setuptools-scm; extra == "dev"
Requires-Dist: sphinx-autobuild; extra == "dev"
Requires-Dist: sphinx; extra == "dev"
Requires-Dist: tox; extra == "dev"
Requires-Dist: twine; extra == "dev"
Dynamic: license-file
